dictionary_navigator/__init__.py
dictionary_navigator/navigator.py
tests/__init__.py
tests/navigator_test.py
dictionary_navigator-1.0.1.dist-info/LICENSE
dictionary_navigator-1.0.1.dist-info/METADATA
dictionary_navigator-1.0.1.dist-info/WHEEL
dictionary_navigator-1.0.1.dist-info/top_level.txt
dictionary_navigator-1.0.1.dist-info/RECORD
