Metadata-Version: 2.1
Name: dictionary-navigator
Version: 1.0.1
Summary: Dictionary Navigator With Strings
Home-page: https://github.com/leeransetton/dictionay_navigator
Author: Leeran Setton
Author-email: leeransetton@gmail.com
License: UNKNOWN
Platform: UNKNOWN
